kryten_llm/__init__.py
kryten_llm/__main__.py
kryten_llm/config.py
kryten_llm/service.py
kryten_llm/components/__init__.py
kryten_llm/components/command_handler.py
kryten_llm/components/config_reloader.py
kryten_llm/components/context_manager.py
kryten_llm/components/formatter.py
kryten_llm/components/health_monitor.py
kryten_llm/components/heartbeat.py
kryten_llm/components/listener.py
kryten_llm/components/llm_manager.py
kryten_llm/components/metrics_server.py
kryten_llm/components/prompt_builder.py
kryten_llm/components/rate_limiter.py
kryten_llm/components/response_logger.py
kryten_llm/components/spam_detector.py
kryten_llm/components/trigger_engine.py
kryten_llm/components/validator.py
kryten_llm/models/__init__.py
kryten_llm/models/config.py
kryten_llm/models/events.py
kryten_llm/models/phase3.py
kryten_llm/utils/__init__.py
kryten_llm/templates/media_change.j2
kryten_llm/templates/system.j2
kryten_llm/templates/trigger.j2
kryten_llm-0.4.6.dist-info/METADATA
kryten_llm-0.4.6.dist-info/WHEEL
kryten_llm-0.4.6.dist-info/entry_points.txt
kryten_llm-0.4.6.dist-info/licenses/LICENSE
kryten_llm-0.4.6.dist-info/RECORD
