Metadata-Version: 2.4
Name: kryten-llm
Version: 0.4.6
Summary: Kryten LLM integration service - provides AI chat responses and interactions
Author: Kryten Robot Team
License: MIT
License-File: LICENSE
Keywords: chat,cytube,microservices,moderation,nats
Classifier: Development Status :: 3 - Alpha
Classifier: Intended Audience :: Developers
Classifier: License :: OSI Approved :: MIT License
Classifier: Programming Language :: Python :: 3
Classifier: Programming Language :: Python :: 3.10
Classifier: Programming Language :: Python :: 3.11
Classifier: Programming Language :: Python :: 3.12
Classifier: Topic :: Communications :: Chat
Classifier: Topic :: Software Development :: Libraries :: Python Modules
Requires-Python: <4.0.0,>=3.10
Requires-Dist: aiohttp<4.0.0,>=3.13.2
Requires-Dist: emoji<3.0.0,>=2.15.0
Requires-Dist: jinja2<4.0.0,>=3.1.6
Requires-Dist: kryten-py>=0.11.5
Requires-Dist: pydantic-settings<3.0.0,>=2.12.0
Requires-Dist: pydantic<3.0.0,>=2.12.5
